langchian/__init__.py
langchian/splitter.py
langchian/template.py
langchian-0.2.1.dist-info/METADATA
langchian-0.2.1.dist-info/WHEEL
langchian-0.2.1.dist-info/top_level.txt
langchian-0.2.1.dist-info/RECORD
